{"rank":1,"score":48,"rating":2419,"username":"Sex_God","performance":2325}
{"rank":2,"score":37,"rating":2226,"username":"Garry_Reason","performance":2299}
{"rank":3,"score":36,"rating":2271,"username":"Lebedevms","performance":2381}
{"rank":4,"score":31,"rating":1971,"username":"navivolin321","performance":2256}
{"rank":5,"score":31,"rating":2122,"username":"kAsparov_dmiTriy","performance":2198}
{"rank":6,"score":19,"rating":2041,"username":"TravelerY","performance":2167}
{"rank":7,"score":18,"rating":2008,"username":"TupikDenis","performance":2127}
{"rank":8,"score":18,"rating":2002,"username":"PashokKotov","performance":1991}
{"rank":9,"score":15,"rating":1850,"username":"Alex_Lavri","performance":1888}
{"rank":10,"score":14,"rating":1963,"username":"Danill_Gasyuk","performance":2051}
{"rank":11,"score":14,"rating":1900,"username":"Demon702","performance":1842}
{"rank":12,"score":14,"rating":2075,"username":"Roma157","performance":1803}
{"rank":13,"score":12,"rating":2048,"username":"Telegin_Dmitriy22","performance":1945}
{"rank":14,"score":7,"rating":1713,"username":"Andreikaluga222","performance":1799}
{"rank":15,"score":5,"rating":2036,"username":"KLOUN_IgorNemzev","performance":1668}
{"rank":16,"score":3,"rating":2184,"username":"cRMSD","performance":1953}
{"rank":17,"score":3,"rating":2158,"username":"Chesstraest2008","performance":1715}
{"rank":18,"score":0,"rating":2112,"username":"Superokcidismutaza"}
{"rank":19,"score":0,"rating":1845,"username":"dimon7226","performance":1461}
